udp-project/udp-code/udp.sv
module udp (
  input  logic        clk,
  input  logic        rst,
  input  logic        r_valid,
  output logic        r_ready,
  input  logic [15:0] r_data,
  input  logic        r_last,
  input  logic        r_keep, // not used currently
  output logic        t_valid,
  input  logic        t_ready,
  output logic [15:0] t_data,
  output logic        t_last,
  output logic [15:0] buffer [3:0],
  output logic [1:0]  r_offset,
  output logic [1:0]  t_offset,
  output logic        t_ready_stall
);

    localparam [1:0] DATA_WIDTH = 2'd3;

    // Using logic types
    // logic [15:0] buffer [3:0];
    // logic [1:0]  r_offset;
    // logic [1:0]  t_offset;

    initial begin
        t_valid  = 1'b0;
        t_last   = 1'b0;
        r_offset = 2'h0;
        t_offset = 2'h0;
        t_ready_stall = 1'b0;
    end

    always_ff @(posedge clk) begin
      if (rst) begin
        t_valid <= 1'b0;
        t_last   <= 1'b0;
        r_offset <= 2'h0;
        t_offset <= 2'h0;
        // rst <= 1'b0;
        buffer[3] <= 16'h0;
        buffer[2] <= 16'h0;
        buffer[1] <= 16'h0;
        buffer[0] <= 16'h0;
      end
    end

    always_ff @(posedge clk) begin
      t_ready_stall <= t_ready;
    end

    // Control r_ready
    always_ff @(posedge clk) begin
      if (r_offset < DATA_WIDTH + 1 && r_valid) begin
        r_ready <= 1'b1;
      end
      else begin
        r_ready <= 1'b0;
      end
    end

    // Control t_last
    // always_ff @(posedge clk) begin
    //   if ((t_offset == DATA_WIDTH - 1) && t_ready) begin
    //      t_last <= 1'b1;
    //   end
    // end

    // Capture incoming data into buffer
    // Shift the buffer and insert new data at buffer[0]
    always_ff @(posedge clk) begin
       if (r_ready && r_valid) begin
        buffer[3] <= r_data;
        buffer[2] <= buffer[3];
        buffer[1] <= buffer[2];
        buffer[0] <= buffer[1];
        // buffer <= {r_data, buffer[3:1]}; Unsupported on verilator version on caddy machine
        if (!r_last) begin
          r_offset <= r_offset + 1;
        end
      end
    end

    always_ff @(posedge clk) begin
      if (t_valid && t_ready) begin
        t_data <= buffer[t_offset];
        if (!t_last) begin
          t_offset <= t_offset + 1;
        end
      end
    end

    // Transfer data from buffer to output
    always_ff @(posedge clk) begin
      if (t_valid && t_ready_stall) begin
        t_valid <= 1'b0;
      end
    end

    // Control t_valid and transition after last data
    always_ff @(posedge clk) begin
      if ((t_offset <= r_offset) && r_last && !r_valid && !t_ready_stall && !t_last && !t_valid && (r_offset > 0)) begin
        t_valid <= 1'b1;
        if (t_offset == r_offset) begin
          t_last <= 1'b1;
        end
      end
    end

/********************  Assertion Defininition  ********************/
`ifdef ABV_ON

property my_property;
  @(posedge clk) r_valid |-> ##1 r_ready; // If 'a' is true at one clock, then 'b' must be true one cycle later
endproperty

assert property(my_property) else $fatal("Assertion failed: Condition not met.");

// always @* begin
//   // ASSUMPTIONS
//   data_bus_valid: assume(r_valid = 1);
  
//   // ASSERTIONS
//   output_never_error: assert(out_d == out + 1);

//   // COVERS
//   data_bus_nonzero: cover(data_bus != '0); 
// end


`endif // ABV_ON


endmodule


/* 
Process Description (After each step formally verify):
1. Create a AXI-stream components
  a. Receive a set of data
  b. Forward this data back to the host using output wires
2. Parse a UDP packet by 1 bit at a time to construct its array for src, dst, len, and checksum
3. Parse an array of protocol being either TCP or UDP
4. Parse an IPv4 packet and set a bool to true or false dependent on TCP or UDP
5. Parse an IPv4 and UDP packet conditionally
6. Parse an ethernet packet 
7. Parse full pipeline



Protocol Designs:
Ethernet: 14 Bytes
 - Destination MAC address (6 bytes)
 - Source MAC address (6 bytes)
 - EtherType/Length field (2 bytes)

IPv4: 20 Bytes
 - Version (4 bits)
 - Header Length (4 bits)
 - DSCP (8 bits)
 - Total Packet Length (16 bits)
 - Id (16 bits)
 - Flags (3 bits)
 - Don't fragment (1 bit)
 - More fragments (1 bit)
 - Fragment offest (13 bit)
 - TTL (8 bits)
 - Protocol (8 bits) 
   - 6 for TCP and 17 for UDP
 - Header Checksum (16 bits)
 - Source Address (32 bits)
 - Destination Address (32 bits)


UDP: 8 Bytes
 - Source port (2 bytes / 16 bits)
 - Destination port (2 bytes / 16 bits)
 - Length (2 bytes / 16 bits)
 - Checksum (2 bytes / 16 bits)
*/

udp-project/udp-code/waveform.vcd
$version Generated by VerilatedVcd $end
$date Wed Dec 18 10:27:56 2024
 $end
$timescale   1ps $end

 $scope module TOP $end
  $var wire 16 . buffer(0) [15:0] $end
  $var wire 16 / buffer(1) [15:0] $end
  $var wire 16 0 buffer(2) [15:0] $end
  $var wire 16 1 buffer(3) [15:0] $end
  $var wire  1 # clk $end
  $var wire 16 ' r_data [15:0] $end
  $var wire  1 ) r_keep $end
  $var wire  1 ( r_last $end
  $var wire  2 2 r_offset [1:0] $end
  $var wire  1 & r_ready $end
  $var wire  1 % r_valid $end
  $var wire  1 $ rst $end
  $var wire 16 , t_data [15:0] $end
  $var wire  1 - t_last $end
  $var wire  2 3 t_offset [1:0] $end
  $var wire  1 + t_ready $end
  $var wire  1 4 t_ready_stall $end
  $var wire  1 * t_valid $end
  $scope module udp $end
   $var wire  2 5 DATA_WIDTH [1:0] $end
   $var wire 16 . buffer(0) [15:0] $end
   $var wire 16 / buffer(1) [15:0] $end
   $var wire 16 0 buffer(2) [15:0] $end
   $var wire 16 1 buffer(3) [15:0] $end
   $var wire  1 # clk $end
   $var wire 16 ' r_data [15:0] $end
   $var wire  1 ) r_keep $end
   $var wire  1 ( r_last $end
   $var wire  2 2 r_offset [1:0] $end
   $var wire  1 & r_ready $end
   $var wire  1 % r_valid $end
   $var wire  1 $ rst $end
   $var wire 16 , t_data [15:0] $end
   $var wire  1 - t_last $end
   $var wire  2 3 t_offset [1:0] $end
   $var wire  1 + t_ready $end
   $var wire  1 4 t_ready_stall $end
   $var wire  1 * t_valid $end
  $upscope $end
 $upscope $end
$enddefinitions $end


#1
0#
1$
0%
0&
b0000000000000000 '
0(
0)
0*
0+
b0000000000000000 ,
0-
b0000000000000000 .
b0000000000000000 /
b0000000000000000 0
b0000000000000000 1
b00 2
b00 3
04
b11 5
#2
1#
#3
0#
0$
#4
1#
#5
0#
#6
1#
#7
0#
#8
1#
#9
0#
#10
1#
#11
0#
#12
1#
#13
0#
#14
1#
1%
1&
b0001000000000000 '
#15
0#
#16
1#
b0001000000000000 1
b01 2
#17
0#
#18
1#
0%
0&
#19
0#
#20
1#
1%
1&
b0001000000000001 '
#21
0#
#22
1#
b0001000000000000 0
b0001000000000001 1
b10 2
#23
0#
#24
1#
0%
0&
#25
0#
#26
1#
1%
1&
b0001000000000010 '
#27
0#
#28
1#
b0001000000000000 /
b0001000000000001 0
b0001000000000010 1
b11 2
#29
0#
#30
1#
0%
0&
#31
0#
#32
1#
1%
1&
b0001000000000011 '
1(
#33
0#
#34
1#
b0001000000000000 .
b0001000000000001 /
b0001000000000010 0
b0001000000000011 1
#35
0#
#36
1#
0%
0&
1*
#37
0#
#38
1#
1+
b0001000000000000 ,
b01 3
14
#39
0#
#40
1#
0*
0+
04
#41
0#
#42
1#
1*
#43
0#
#44
1#
1+
b0001000000000001 ,
b10 3
14
#45
0#
#46
1#
0*
0+
04
#47
0#
#48
1#
1*
#49
0#
#50
1#
1+
b0001000000000010 ,
b11 3
14
#51
0#
#52
1#
0*
0+
04
#53
0#
#54
1#
1*
1-
#55
0#
#56
1#
1+
b0001000000000011 ,
14
#57
0#
#58
1#
0*
0+
04
#59
0#
1$
b0000000000000000 '
0(
#60
1#
0-
b0000000000000000 .
b0000000000000000 /
b0000000000000000 0
b0000000000000000 1
b00 2
b00 3
#61
0#
0$
#62
1#
#63
0#
#64
1#
#65
0#
#66
1#
#67
0#
#68
1#
#69
0#
#70
1#
#71
0#
#72
1#
1%
1&
b0001000000000000 '
#73
0#
#74
1#
b0001000000000000 1
b01 2
#75
0#
#76
1#
0%
0&
#77
0#
#78
1#
1%
1&
b0001000000000001 '
#79
0#
#80
1#
b0001000000000000 0
b0001000000000001 1
b10 2
#81
0#
#82
1#
0%
0&
#83
0#
#84
1#
1%
1&
b0001000000000010 '
#85
0#
#86
1#
b0001000000000000 /
b0001000000000001 0
b0001000000000010 1
b11 2
#87
0#
#88
1#
0%
0&
#89
0#
#90
1#
1%
1&
b0001000000000011 '
1(
#91
0#
#92
1#
b0001000000000000 .
b0001000000000001 /
b0001000000000010 0
b0001000000000011 1
#93
0#
#94
1#
0%
0&
1*
#95
0#
#96
1#
1+
b0001000000000000 ,
b01 3
14
#97
0#
#98
1#
0*
0+
04
#99
0#
#100
1#
1*
#101
0#
#102
1#
1+
b0001000000000001 ,
b10 3
14
#103
0#
#104
1#
0*
0+
04
#105
0#
#106
1#
1*
#107
0#
#108
1#
1+
b0001000000000010 ,
b11 3
14
#109
0#
#110
1#
0*
0+
04
#111
0#
#112
1#
1*
1-
#113
0#
#114
1#
1+
b0001000000000011 ,
14
#115
0#
#116
1#
0*
0+
04
