udp-project/udp-code/udp.v
module udp(
  input wire clk,
  input wire r_valid,
  output reg r_ready,
  input wire [15:0] r_data,
  input wire r_last,
  input wire r_keep, // not sure how to use this
  output reg t_valid,
  // output reg [15:0] buffer [3:0],
  input wire t_ready,
  output reg [15:0] t_data,
  output reg t_last
  // output reg[1:0] t_offset,
  // output reg[1:0] r_offset
);

    localparam DATA_WIDTH = 2'd3;
    initial t_valid = 0;
    initial t_last = 0;
    initial r_offset = 2'h0;
    reg [15:0] buffer [3:0];
    reg [1:0] r_offset = 0;
    reg [1:0] t_offset = 0;


    always @ (posedge clk) begin
      if (r_offset < DATA_WIDTH + 1) begin
        r_ready <= r_valid;
      end
    end  
    
    always @ (posedge clk) begin
      if (t_offset == DATA_WIDTH - 1 && t_ready) begin
         t_last <= 1'b1;
      end
    end 

    //if tready get r_tdata into t_tdata
    always @ (posedge clk) begin
      if (r_ready) begin
        buffer <= {r_data, buffer[3:1]};
        if (!r_last) begin
          r_offset <= r_offset + 1;
        end
      end
    end

    always @ (posedge clk) begin
      if (t_valid)
      begin
        t_data <= buffer[t_offset];
        if (t_ready && !t_last) begin
          t_offset <= t_offset + 1;
        end
      end
    end 

    //if r_last then t_last
    always @ (posedge clk) begin
      if (t_offset < r_offset && r_last && !r_valid)
      begin
        t_valid <= 1'b1;
      end

      else if ((t_last && t_ready) || (t_valid && t_ready))
      begin
        t_valid <= 1'b0;
      end 
    end 


endmodule

/* 
Process Description (After each step formally verify):
1. Create a AXI-stream components
  a. Receive a set of data
  b. Forward this data back to the host using output wires
2. Parse a UDP packet by 1 bit at a time to construct its array for src, dst, len, and checksum
3. Parse an array of protocol being either TCP or UDP
4. Parse an IPv4 packet and set a bool to true or false dependent on TCP or UDP
5. Parse an IPv4 and UDP packet conditionally
6. Parse an ethernet packet 
7. Parse full pipeline



Protocol Designs:
Ethernet: 14 Bytes
 - Destination MAC address (6 bytes)
 - Source MAC address (6 bytes)
 - EtherType/Length field (2 bytes)

IPv4: 20 Bytes
 - Version (4 bits)
 - Header Length (4 bits)
 - DSCP (8 bits)
 - Total Packet Length (16 bits)
 - Id (16 bits)
 - Flags (3 bits)
 - Don't fragment (1 bit)
 - More fragments (1 bit)
 - Fragment offest (13 bit)
 - TTL (8 bits)
 - Protocol (8 bits) 
   - 6 for TCP and 17 for UDP
 - Header Checksum (16 bits)
 - Source Address (32 bits)
 - Destination Address (32 bits)


UDP: 8 Bytes
 - Source port (2 bytes / 16 bits)
 - Destination port (2 bytes / 16 bits)
 - Length (2 bytes / 16 bits)
 - Checksum (2 bytes / 16 bits)
*/

udp-project/udp-code/waveform.vcd
$version Generated by VerilatedVcd $end
$timescale 1ps $end
 $scope module TOP $end
  $var wire 1 ) clk $end
  $var wire 1 * r_valid $end
  $var wire 1 + r_ready $end
  $var wire 16 , r_data [15:0] $end
  $var wire 1 - r_last $end
  $var wire 1 . r_keep $end
  $var wire 1 / t_valid $end
  $var wire 1 0 t_ready $end
  $var wire 16 1 t_data [15:0] $end
  $var wire 1 2 t_last $end
  $scope module udp $end
   $var wire 1 ) clk $end
   $var wire 1 * r_valid $end
   $var wire 1 + r_ready $end
   $var wire 16 , r_data [15:0] $end
   $var wire 1 - r_last $end
   $var wire 1 . r_keep $end
   $var wire 1 / t_valid $end
   $var wire 1 0 t_ready $end
   $var wire 16 1 t_data [15:0] $end
   $var wire 1 2 t_last $end
   $var wire 2 3 DATA_WIDTH [1:0] $end
   $var wire 16 # buffer[0] [15:0] $end
   $var wire 16 $ buffer[1] [15:0] $end
   $var wire 16 % buffer[2] [15:0] $end
   $var wire 16 & buffer[3] [15:0] $end
   $var wire 2 ' r_offset [1:0] $end
   $var wire 2 ( t_offset [1:0] $end
  $upscope $end
 $upscope $end
$enddefinitions $end


#1
b0000000000000000 #
b0000000000000000 $
b0000000000000000 %
b0000000000000000 &
b00 '
b00 (
0)
0*
0+
b0000000000000000 ,
0-
0.
0/
00
b0000000000000000 1
02
b11 3
#2
1)
#3
0)
#4
1)
#5
0)
#6
1)
#7
0)
#8
1)
#9
0)
#10
1)
#11
0)
1*
b0001000000000000 ,
#12
1)
1+
#13
0)
0*
#14
b0001000000000000 &
b01 '
1)
0+
#15
0)
1*
b0001000000000001 ,
#16
1)
1+
#17
0)
0*
#18
b0001000000000000 %
b0001000000000001 &
b10 '
1)
0+
#19
0)
1*
b0001000000000010 ,
#20
1)
1+
#21
0)
0*
#22
b0001000000000000 $
b0001000000000001 %
b0001000000000010 &
b11 '
1)
0+
#23
0)
1*
b0001000000000011 ,
1-
#24
1)
1+
#25
0)
0*
#26
b0001000000000000 #
b0001000000000001 $
b0001000000000010 %
b0001000000000011 &
1)
0+
1/
#27
0)
#28
1)
b0001000000000000 1
#29
0)
10
#30
b01 (
1)
#31
0)
00
#32
1)
b0001000000000001 1
#33
0)
#34
1)
#35
0)
10
#36
b10 (
1)
#37
0)
00
#38
1)
b0001000000000010 1
#39
0)
#40
1)
#41
0)
10
#42
b11 (
1)
12
#43
0)
00
#44
1)
b0001000000000011 1
#45
0)
#46
1)
#47
0)
10
#48
1)
0/
#49
0)
00
